Deployment/__init__.py
Deployment/admin.py
Deployment/apps.py
Deployment/forms.py
Deployment/models.py
Deployment/tests.py
Deployment/urls.py
Deployment/views.py
Deployment/migrations/0001_initial.py
Deployment/migrations/0002_auto_20211007_1724.py
Deployment/migrations/0003_pickle.py
Deployment/migrations/0004_alter_pickle_pickle_file.py
Deployment/migrations/__init__.py
Deployment/static/css/a.css
Deployment/static/css/all.min.css
Deployment/static/css/b.css
Deployment/static/css/bootstrap.min.css
Deployment/static/css/c.css
Deployment/static/css/d.css
Deployment/static/css/smtp1.css
Deployment/static/css/smtp2.css
Deployment/static/css/smtp3.css
Deployment/static/css/smtp4.css
Deployment/static/css/smtp5.css
Deployment/static/css/style.min.css
Deployment/static/images/bg.svg
Deployment/templates/Deployment/home.html
Naga_Ml_Model_Apps-0.0.3.dist-info/LICENSE.txt
Naga_Ml_Model_Apps-0.0.3.dist-info/METADATA
Naga_Ml_Model_Apps-0.0.3.dist-info/WHEEL
Naga_Ml_Model_Apps-0.0.3.dist-info/top_level.txt
Naga_Ml_Model_Apps-0.0.3.dist-info/RECORD
