Metadata-Version: 2.1
Name: Naga-Ml-Model-Apps
Version: 0.0.3
Summary: This Package is used to Predict house prices in Aus based on house type
Home-page: https://github.com/Nagababu91768/house-price-prediction-ml-app
Author: Upputuri Nagababu
Author-email: nagababuuupputuri@gmail.com
License: MIT  # Example license
Platform: UNKNOWN
Classifier: Environment :: Web Environment
Classifier: Framework :: Django
Classifier: Framework :: Django
Classifier: Intended Audience :: Developers
Classifier: License :: OSI Approved :: MIT License
Classifier: Operating System :: OS Independent
Classifier: Programming Language :: Python :: 3.9
Classifier: Programming Language :: Python :: 3.6
Classifier: Programming Language :: Python :: 3.7
Classifier: Programming Language :: Python :: 3.8
Classifier: Topic :: Internet :: WWW/HTTP
Classifier: Topic :: Internet :: WWW/HTTP :: Dynamic Content
Requires-Python: >=3.6
License-File: LICENSE.txt
Requires-Dist: Django
Requires-Dist: crispy
Requires-Dist: django-crispy-forms
Requires-Dist: django-widget-tweaks
Requires-Dist: Pillow
Requires-Dist: numpy
Requires-Dist: pandas
Requires-Dist: sklearn
Requires-Dist: matplotlib
Requires-Dist: seaborn
Requires-Dist: psycopg2
Requires-Dist: pymongo
